tradutor/__init__.py
tradutor/tradutor_pten.py
tradutor/translate_enpt.py
tradutor-0.0.1.dist-info/METADATA
tradutor-0.0.1.dist-info/WHEEL
tradutor-0.0.1.dist-info/top_level.txt
tradutor-0.0.1.dist-info/RECORD
