Metadata-Version: 2.1
Name: tradutor
Version: 0.0.1
Summary: Translate English into Portuguese and Portuguese into English
Home-page: https://github.com/prtdiniz/tradutor.git
Author: Paulo Ricardo Diniz
Author-email: prtdiniz@hotmail.com
License: UNKNOWN
Platform: UNKNOWN
Requires-Python: >=3.8
Requires-Dist: translators
